.gitignore
COPYING
README.md
pyproject.toml
setup.py
.github/workflows/pythonpackage.yml
.github/workflows/wheels.yaml
catalogus/__init__.py
catalogus/pyutils.py
catalogus/registry.py
catalogus.egg-info/PKG-INFO
catalogus.egg-info/SOURCES.txt
catalogus.egg-info/dependency_links.txt
catalogus.egg-info/requires.txt
catalogus.egg-info/top_level.txt
tests/test_pyutils.py
tests/test_registry.py