Metadata-Version: 2.4
Name: catalogus
Version: 0.1.0
Summary: Classes to provide name-to-object registry-like support
Author-email: Breezy Developers <breezy-core@googlegroups.com>
Maintainer-email: Breezy Developers <breezy-core@googlegroups.com>
License: GPL-2.0-or-later
Project-URL: Homepage, https://github.com/breezy-team/catalogus
Project-URL: Bug Tracker, https://github.com/breezy-team/catalogus/issues
Project-URL: Source Code, https://github.com/breezy-team/catalogus
Keywords: registry,plugin,extensibility
Classifier: Development Status :: 4 - Beta
Classifier: Intended Audience :: Developers
Classifier: License :: OSI Approved :: GNU General Public License v2 or later (GPLv2+)
Classifier: Operating System :: OS Independent
Classifier: Programming Language :: Python
Classifier: Programming Language :: Python :: 3
Classifier: Programming Language :: Python :: 3.9
Classifier: Programming Language :: Python :: 3.10
Classifier: Programming Language :: Python :: 3.11
Classifier: Programming Language :: Python :: 3.12
Classifier: Programming Language :: Python :: 3.13
Classifier: Topic :: Software Development :: Libraries :: Python Modules
Requires-Python: >=3.9
License-File: COPYING
Provides-Extra: dev
Requires-Dist: mypy>=1.0; extra == "dev"
Requires-Dist: pytest-cov>=4.0; extra == "dev"
Requires-Dist: pytest>=7.0; extra == "dev"
Requires-Dist: ruff>=0.1.0; extra == "dev"
Dynamic: license-file
